aemet_opendata/__init__.py
aemet_opendata/const.py
aemet_opendata/exceptions.py
aemet_opendata/forecast.py
aemet_opendata/helpers.py
aemet_opendata/interface.py
aemet_opendata/py.typed
aemet_opendata/radar.py
aemet_opendata/station.py
aemet_opendata/town.py
AEMET_OpenData-0.6.3.dist-info/LICENSE.md
AEMET_OpenData-0.6.3.dist-info/METADATA
AEMET_OpenData-0.6.3.dist-info/WHEEL
AEMET_OpenData-0.6.3.dist-info/top_level.txt
AEMET_OpenData-0.6.3.dist-info/RECORD
