Metadata-Version: 2.1
Name: AEMET-OpenData
Version: 0.6.3
Summary: AEMET OpenData Rest API library
Author-email: Álvaro Fernández Rojas <noltari@gmail.com>
License: GPL-2.0-only
Project-URL: Homepage, https://github.com/Noltari/AEMET-OpenData
Project-URL: Bug Tracker, https://github.com/Noltari/AEMET-OpenData/issues
Keywords: AEMET,weather,forecast,home
Platform: any
Classifier: Development Status :: 4 - Beta
Classifier: Intended Audience :: Developers
Classifier: Natural Language :: English
Classifier: Programming Language :: Python :: 3
Classifier: Programming Language :: Python :: 3.11
Classifier: Programming Language :: Python :: 3.12
Classifier: Programming Language :: Python :: 3.13
Classifier: Topic :: Home Automation
Requires-Python: >=3.11
License-File: LICENSE.md
Requires-Dist: aiohttp
Requires-Dist: geopy
